heartloglost/GoogleTTS.py
heartloglost/__init__.py
heartloglost/abyss.py
heartloglost/compressvideo.py
heartloglost/fileio.py
heartloglost/fileslion.py
heartloglost/getpasscolab.py
heartloglost/gofiles.py
heartloglost/hllostclient.py
heartloglost/pixeldrain.py
heartloglost/pypdl.py
heartloglost/reqsession.py
heartloglost/shell.py
heartloglost/streamtape.py
heartloglost/streamtapedl.py
heartloglost/telegrampy.py
heartloglost/torrent.py
heartloglost/ulty.py
heartloglost-0.7.31.dist-info/licenses/LICENSE
heartloglost-0.7.31.dist-info/METADATA
heartloglost-0.7.31.dist-info/WHEEL
heartloglost-0.7.31.dist-info/top_level.txt
heartloglost-0.7.31.dist-info/RECORD
