Metadata-Version: 2.4
Name: heartloglost
Version: 0.7.31
Summary: No info.
Author: Heartlog
Keywords: heartlog,new
Classifier: Programming Language :: Python :: 3
Classifier: Programming Language :: Python :: 3.7
Classifier: Programming Language :: Python :: 3.8
Classifier: Programming Language :: Python :: 3.9
Classifier: Programming Language :: Python :: 3.10
Classifier: Programming Language :: Python :: 3.11
Classifier: Operating System :: OS Independent
Classifier: License :: OSI Approved :: MIT License
Classifier: Natural Language :: English
Requires-Python: >=3.8
License-File: LICENSE
Requires-Dist: requests
Requires-Dist: beautifulsoup4
Requires-Dist: PyBypass
Requires-Dist: ffmpeg-python
Requires-Dist: pypdl
Requires-Dist: pyrogram
Requires-Dist: gTTS
Requires-Dist: fake_useragent
Requires-Dist: python-dotenv
Dynamic: license-file
